pypyraws/__init__.py
pypyraws/contextargs.py
pypyraws/errors.py
pypyraws/version.py
pypyraws/aws/__init__.py
pypyraws/aws/s3.py
pypyraws/aws/service.py
pypyraws/steps/__init__.py
pypyraws/steps/client.py
pypyraws/steps/ecswaitprep.py
pypyraws/steps/s3fetchjson.py
pypyraws/steps/s3fetchyaml.py
pypyraws/steps/wait.py
pypyraws/steps/waitfor.py
pypyraws-1.3.0.dist-info/LICENSE
pypyraws-1.3.0.dist-info/METADATA
pypyraws-1.3.0.dist-info/WHEEL
pypyraws-1.3.0.dist-info/top_level.txt
pypyraws-1.3.0.dist-info/RECORD
