Metadata-Version: 2.1
Name: pypyraws
Version: 1.3.0
Summary: pypyr task runner AWS plugin. Automate services like ECS, S3, Beanstalk & EC2 with automation pipelines without writing having to write code.
Home-page: https://pypyr.io/
Author: Thomas Gaigher
Author-email: info@pypyr.io
License: Apache License 2.0
Project-URL: Documentation, https://pypyr.io/docs/plugins/aws/
Project-URL: Source, https://github.com/pypyr/pypyr-aws
Project-URL: Release notes, https://pypyr.io/updates/releases/
Project-URL: Tracker, https://github.com/pypyr/pypyr-aws/issues/
Keywords: pypyr,aws,plugin,devops,task-runner,pipeline,automation
Platform: UNKNOWN
Classifier: Development Status :: 5 - Production/Stable
Classifier: Intended Audience :: Developers
Classifier: Topic :: Software Development :: Build Tools
Classifier: Topic :: Software Development :: Libraries :: Python Modules
Classifier: License :: OSI Approved :: Apache Software License
Classifier: Programming Language :: Python :: 3.7
Classifier: Programming Language :: Python :: 3.8
Classifier: Programming Language :: Python :: 3.9
Classifier: Programming Language :: Python :: 3.10
License-File: LICENSE
Requires-Dist: pypyr
Requires-Dist: boto3
Requires-Dist: ruamel.yaml
Provides-Extra: dev
Requires-Dist: bumpversion ; extra == 'dev'
Requires-Dist: codecov ; extra == 'dev'
Requires-Dist: flake8 ; extra == 'dev'
Requires-Dist: flake8-docstrings ; extra == 'dev'
Requires-Dist: pypyr ; extra == 'dev'
Requires-Dist: pytest ; extra == 'dev'
Requires-Dist: pytest-cov ; extra == 'dev'
Requires-Dist: setuptools ; extra == 'dev'
Requires-Dist: twine ; extra == 'dev'
Requires-Dist: wheel ; extra == 'dev'
